.bzrignore
HISTORY.txt
README.txt
setup.cfg
setup.py
collective/__init__.py
collective.recipe.scriptgen.egg-info/PKG-INFO
collective.recipe.scriptgen.egg-info/SOURCES.txt
collective.recipe.scriptgen.egg-info/dependency_links.txt
collective.recipe.scriptgen.egg-info/entry_points.txt
collective.recipe.scriptgen.egg-info/namespace_packages.txt
collective.recipe.scriptgen.egg-info/not-zip-safe
collective.recipe.scriptgen.egg-info/requires.txt
collective.recipe.scriptgen.egg-info/top_level.txt
collective/recipe/__init__.py
collective/recipe/scriptgen/__init__.py
collective/recipe/scriptgen/ctl.py