Metadata-Version: 1.0
Name: collective.recipe.scriptgen
Version: 0.2
Summary: zc.buildout recipe for generating a script
Home-page: http://svn.plone.org/svn/collective/buildout/collective.recipe.scriptgen
Author: Rocky Burt
Author-email: rocky@serverzen.com
License: ZPL
Platform: UNKNOWN
Classifier: Framework :: Buildout
Classifier: Intended Audience :: Developers
Classifier: Topic :: Software Development :: Build Tools
Classifier: Topic :: Software Development :: Libraries :: Python Modules
Classifier: License :: OSI Approved :: Zope Public License
